[
    {
        "title": "logo.png",
        "description": "logo",
        "file": "logo.png"
    },
    {
        "title": "logo.png",
        "description": "logo",
        "file": "logo.png"
    },
    {
        "title": "concept-dsr.gif",
        "description": "Direct",
        "file": "concept-dsr.gif"
    },
    {
        "title": "How-VPN-works.jpg",
        "description": "Internal Server",
        "file": "How-VPN-works.jpg"
    },
    {
        "title": "Screenshot-2022-10-17-at-5.27.27-PM-2048x1606.png",
        "description": "DNS",
        "file": "Screenshot-2022-10-17-at-5.27.27-PM-2048x1606.png"
    },
    {
        "title": "181827567",
        "description": "AzadiDNS",
        "file": "181827567"
    },
    {
        "title": "155004885",
        "description": "BPB",
        "file": "155004885"
    },
    {
        "title": "Screenshot-2018-02-01-09.20.49_preview.png",
        "description": "Worker",
        "file": "Screenshot-2018-02-01-09.20.49_preview.png"
    },
    {
        "title": "altcoins.png",
        "description": "Buy",
        "file": "altcoins.png"
    },
    {
        "title": "201552920-ed6eca0d-b89c-47ee-a4b3-c65a0b36b90a.png",
        "description": "Panel",
        "file": "201552920-ed6eca0d-b89c-47ee-a4b3-c65a0b36b90a.png"
    },
    {
        "title": "%D8%B4%D8%A8%DA%A9%D9%87-1-1.jpg",
        "description": "Server Security",
        "file": "%D8%B4%D8%A8%DA%A9%D9%87-1-1.jpg"
    },
    {
        "title": "media-server-home.jpg",
        "description": "Home Server",
        "file": "media-server-home.jpg"
    },
    {
        "title": "unnamed-file-4.jpg",
        "description": "Oracle",
        "file": "unnamed-file-4.jpg"
    },
    {
        "title": "220px-Fastly_logo.svg.png",
        "description": "Fastly",
        "file": "220px-Fastly_logo.svg.png"
    },
    {
        "title": "Gcore_Logo.jpg",
        "description": "Gcore",
        "file": "Gcore_Logo.jpg"
    },
    {
        "title": "a40da6d2-3f95-4680-bd39-b6b7996459c7-permlink.jpg",
        "description": "Oblivion",
        "file": "a40da6d2-3f95-4680-bd39-b6b7996459c7-permlink.jpg"
    },
    {
        "title": "227777845-a4d0f86b-faa2-4f2b-a410-4aa5f68bfe19.png",
        "description": "Hiddify",
        "file": "227777845-a4d0f86b-faa2-4f2b-a410-4aa5f68bfe19.png"
    },
    {
        "title": "images",
        "description": "Donate",
        "file": "images"
    },
    {
        "title": "1704897422-sing-box-releases-1024x538.jpg.avif",
        "description": "Singbox",
        "file": "1704897422-sing-box-releases-1024x538.jpg.avif"
    },
    {
        "title": "1280px-Client-server-model.svg.png",
        "description": "Clients",
        "file": "1280px-Client-server-model.svg.png"
    },
    {
        "title": "hq720.jpg",
        "description": "Xhttp",
        "file": "hq720.jpg"
    },
    {
        "title": "121px-Telegram_2019_Logo.svg.png",
        "description": "Telegram",
        "file": "121px-Telegram_2019_Logo.svg.png"
    },
    {
        "title": "images",
        "description": "Brook",
        "file": "images"
    },
    {
        "title": "tixGgVipnsaKeGQzykJfgSEhUc_YYMSsr3gwBuPTpXb2F1BKPVzv5OxfCrpS8OAXXh8",
        "description": "Wireguard",
        "file": "tixGgVipnsaKeGQzykJfgSEhUc_YYMSsr3gwBuPTpXb2F1BKPVzv5OxfCrpS8OAXXh8"
    },
    {
        "title": "images",
        "description": "IPV6",
        "file": "images"
    },
    {
        "title": "uaI3dD2oXRVNECCXbTjcVe05tP-jTGOSUB2VAoR3JEEkHqrdpyNqHW6grKge5elSk2I",
        "description": "VPNhood",
        "file": "uaI3dD2oXRVNECCXbTjcVe05tP-jTGOSUB2VAoR3JEEkHqrdpyNqHW6grKge5elSk2I"
    },
    {
        "title": "maxresdefault.jpg",
        "description": "UDP",
        "file": "maxresdefault.jpg"
    },
    {
        "title": "maxresdefault.jpg",
        "description": "Cloak",
        "file": "maxresdefault.jpg"
    },
    {
        "title": "146542574",
        "description": "Bepass",
        "file": "146542574"
    },
    {
        "title": "Twitter-New-Logo-X-2023-.jpg",
        "description": "Twitter",
        "file": "Twitter-New-Logo-X-2023-.jpg"
    },
    {
        "title": "WhatsApp.svg",
        "description": "Twitter",
        "file": "WhatsApp.svg"
    },
    {
        "title": "information-protection-governance.svg",
        "description": "Protection",
        "file": "information-protection-governance.svg"
    },
    {
        "title": "300px-Persian-encyclopedia.jpg",
        "description": "Knowledge Base",
        "file": "300px-Persian-encyclopedia.jpg"
    },
    {
        "title": "UtDq3fd8_400x400.jpg",
        "description": "ISegaro",
        "file": "UtDq3fd8_400x400.jpg"
    },
    {
        "title": "Back-to-Basics-1024x536.jpg",
        "description": "Primary",
        "file": "Back-to-Basics-1024x536.jpg"
    },
    {
        "title": "What-is-an-API.png",
        "description": "API",
        "file": "What-is-an-API.png"
    },
    {
        "title": "AI-Artificial-Intelligence-What-it-is-and-why-it-matters-qb1o8gpaeu2d4z5h27m45d99w1tmlkjwinh4wq1izi.jpg",
        "description": "Robots",
        "file": "AI-Artificial-Intelligence-What-it-is-and-why-it-matters-qb1o8gpaeu2d4z5h27m45d99w1tmlkjwinh4wq1izi.jpg"
    },
    {
        "title": "oneline-sitemap-2093%C3%97627px-2048x614.webp",
        "description": "API",
        "file": "oneline-sitemap-2093%C3%97627px-2048x614.webp"
    },
    {
        "title": "141410815",
        "description": "No description",
        "file": "141410815"
    },
    {
        "title": "googlelogo_color_272x92dp.png",
        "description": "No description",
        "file": "googlelogo_color_272x92dp.png"
    },
    {
        "title": "images",
        "description": "Experience",
        "file": "images"
    },
    {
        "title": "youtube-subscribe-png.png",
        "description": "Subscribe",
        "file": "youtube-subscribe-png.png"
    },
    {
        "title": "BDJ_Team_Top_Tips_Hero_Image-3f7a305d00baa5d40ac3d84ad0de44c4.jpg",
        "description": "Tips",
        "file": "BDJ_Team_Top_Tips_Hero_Image-3f7a305d00baa5d40ac3d84ad0de44c4.jpg"
    },
    {
        "title": "300px-National_intranet_of_Iran.svg.png",
        "description": "People",
        "file": "300px-National_intranet_of_Iran.svg.png"
    },
    {
        "title": "slider-projects-default.png",
        "description": "Fund",
        "file": "slider-projects-default.png"
    },
    {
        "title": "What-is-Research-Purpose-of-Research-phul4s3cbwe0xam190dnc4kz3z616ajmfkygodcdqg.png",
        "description": "Research",
        "file": "What-is-Research-Purpose-of-Research-phul4s3cbwe0xam190dnc4kz3z616ajmfkygodcdqg.png"
    },
    {
        "title": "GJIkGXNX_400x400.jpg",
        "description": "Yebekhe",
        "file": "GJIkGXNX_400x400.jpg"
    },
    {
        "title": "159781143",
        "description": "Page_4n0nymou3",
        "file": "159781143"
    },
    {
        "title": "a0959131344_16.jpg",
        "description": "Fragment",
        "file": "a0959131344_16.jpg"
    },
    {
        "title": "images",
        "description": "Film",
        "file": "images"
    },
    {
        "title": "other_icon.png",
        "description": "Other",
        "file": "other_icon.png"
    },
    {
        "title": "logo.png",
        "description": "logo",
        "file": "logo.png"
    },
    {
        "title": "logo.png",
        "description": "logo",
        "file": "logo.png"
    },
    {
        "title": "concept-dsr.gif",
        "description": "Direct",
        "file": "concept-dsr.gif"
    },
    {
        "title": "How-VPN-works.jpg",
        "description": "Internal Server",
        "file": "How-VPN-works.jpg"
    },
    {
        "title": "Screenshot-2022-10-17-at-5.27.27-PM-2048x1606.png",
        "description": "DNS",
        "file": "Screenshot-2022-10-17-at-5.27.27-PM-2048x1606.png"
    },
    {
        "title": "181827567",
        "description": "AzadiDNS",
        "file": "181827567"
    },
    {
        "title": "155004885",
        "description": "BPB",
        "file": "155004885"
    },
    {
        "title": "Screenshot-2018-02-01-09.20.49_preview.png",
        "description": "Worker",
        "file": "Screenshot-2018-02-01-09.20.49_preview.png"
    },
    {
        "title": "altcoins.png",
        "description": "Buy",
        "file": "altcoins.png"
    },
    {
        "title": "201552920-ed6eca0d-b89c-47ee-a4b3-c65a0b36b90a.png",
        "description": "Panel",
        "file": "201552920-ed6eca0d-b89c-47ee-a4b3-c65a0b36b90a.png"
    },
    {
        "title": "%D8%B4%D8%A8%DA%A9%D9%87-1-1.jpg",
        "description": "Server Security",
        "file": "%D8%B4%D8%A8%DA%A9%D9%87-1-1.jpg"
    },
    {
        "title": "media-server-home.jpg",
        "description": "Home Server",
        "file": "media-server-home.jpg"
    },
    {
        "title": "unnamed-file-4.jpg",
        "description": "Oracle",
        "file": "unnamed-file-4.jpg"
    },
    {
        "title": "220px-Fastly_logo.svg.png",
        "description": "Fastly",
        "file": "220px-Fastly_logo.svg.png"
    },
    {
        "title": "Gcore_Logo.jpg",
        "description": "Gcore",
        "file": "Gcore_Logo.jpg"
    },
    {
        "title": "a40da6d2-3f95-4680-bd39-b6b7996459c7-permlink.jpg",
        "description": "Oblivion",
        "file": "a40da6d2-3f95-4680-bd39-b6b7996459c7-permlink.jpg"
    },
    {
        "title": "227777845-a4d0f86b-faa2-4f2b-a410-4aa5f68bfe19.png",
        "description": "Hiddify",
        "file": "227777845-a4d0f86b-faa2-4f2b-a410-4aa5f68bfe19.png"
    },
    {
        "title": "images",
        "description": "Donate",
        "file": "images"
    },
    {
        "title": "1704897422-sing-box-releases-1024x538.jpg.avif",
        "description": "Singbox",
        "file": "1704897422-sing-box-releases-1024x538.jpg.avif"
    },
    {
        "title": "1280px-Client-server-model.svg.png",
        "description": "Clients",
        "file": "1280px-Client-server-model.svg.png"
    },
    {
        "title": "hq720.jpg",
        "description": "Xhttp",
        "file": "hq720.jpg"
    },
    {
        "title": "121px-Telegram_2019_Logo.svg.png",
        "description": "Telegram",
        "file": "121px-Telegram_2019_Logo.svg.png"
    },
    {
        "title": "images",
        "description": "Brook",
        "file": "images"
    },
    {
        "title": "tixGgVipnsaKeGQzykJfgSEhUc_YYMSsr3gwBuPTpXb2F1BKPVzv5OxfCrpS8OAXXh8",
        "description": "Wireguard",
        "file": "tixGgVipnsaKeGQzykJfgSEhUc_YYMSsr3gwBuPTpXb2F1BKPVzv5OxfCrpS8OAXXh8"
    },
    {
        "title": "images",
        "description": "IPV6",
        "file": "images"
    },
    {
        "title": "uaI3dD2oXRVNECCXbTjcVe05tP-jTGOSUB2VAoR3JEEkHqrdpyNqHW6grKge5elSk2I",
        "description": "VPNhood",
        "file": "uaI3dD2oXRVNECCXbTjcVe05tP-jTGOSUB2VAoR3JEEkHqrdpyNqHW6grKge5elSk2I"
    },
    {
        "title": "maxresdefault.jpg",
        "description": "UDP",
        "file": "maxresdefault.jpg"
    },
    {
        "title": "maxresdefault.jpg",
        "description": "Cloak",
        "file": "maxresdefault.jpg"
    },
    {
        "title": "146542574",
        "description": "Bepass",
        "file": "146542574"
    },
    {
        "title": "Twitter-New-Logo-X-2023-.jpg",
        "description": "Twitter",
        "file": "Twitter-New-Logo-X-2023-.jpg"
    },
    {
        "title": "WhatsApp.svg",
        "description": "Twitter",
        "file": "WhatsApp.svg"
    },
    {
        "title": "information-protection-governance.svg",
        "description": "Protection",
        "file": "information-protection-governance.svg"
    },
    {
        "title": "300px-Persian-encyclopedia.jpg",
        "description": "Knowledge Base",
        "file": "300px-Persian-encyclopedia.jpg"
    },
    {
        "title": "UtDq3fd8_400x400.jpg",
        "description": "ISegaro",
        "file": "UtDq3fd8_400x400.jpg"
    },
    {
        "title": "Back-to-Basics-1024x536.jpg",
        "description": "Primary",
        "file": "Back-to-Basics-1024x536.jpg"
    },
    {
        "title": "What-is-an-API.png",
        "description": "API",
        "file": "What-is-an-API.png"
    },
    {
        "title": "AI-Artificial-Intelligence-What-it-is-and-why-it-matters-qb1o8gpaeu2d4z5h27m45d99w1tmlkjwinh4wq1izi.jpg",
        "description": "Robots",
        "file": "AI-Artificial-Intelligence-What-it-is-and-why-it-matters-qb1o8gpaeu2d4z5h27m45d99w1tmlkjwinh4wq1izi.jpg"
    },
    {
        "title": "oneline-sitemap-2093%C3%97627px-2048x614.webp",
        "description": "API",
        "file": "oneline-sitemap-2093%C3%97627px-2048x614.webp"
    },
    {
        "title": "141410815",
        "description": "No description",
        "file": "141410815"
    },
    {
        "title": "googlelogo_color_272x92dp.png",
        "description": "No description",
        "file": "googlelogo_color_272x92dp.png"
    },
    {
        "title": "images",
        "description": "Experience",
        "file": "images"
    },
    {
        "title": "youtube-subscribe-png.png",
        "description": "Subscribe",
        "file": "youtube-subscribe-png.png"
    },
    {
        "title": "BDJ_Team_Top_Tips_Hero_Image-3f7a305d00baa5d40ac3d84ad0de44c4.jpg",
        "description": "Tips",
        "file": "BDJ_Team_Top_Tips_Hero_Image-3f7a305d00baa5d40ac3d84ad0de44c4.jpg"
    },
    {
        "title": "300px-National_intranet_of_Iran.svg.png",
        "description": "People",
        "file": "300px-National_intranet_of_Iran.svg.png"
    },
    {
        "title": "slider-projects-default.png",
        "description": "Fund",
        "file": "slider-projects-default.png"
    },
    {
        "title": "What-is-Research-Purpose-of-Research-phul4s3cbwe0xam190dnc4kz3z616ajmfkygodcdqg.png",
        "description": "Research",
        "file": "What-is-Research-Purpose-of-Research-phul4s3cbwe0xam190dnc4kz3z616ajmfkygodcdqg.png"
    },
    {
        "title": "GJIkGXNX_400x400.jpg",
        "description": "Yebekhe",
        "file": "GJIkGXNX_400x400.jpg"
    },
    {
        "title": "159781143",
        "description": "Page_4n0nymou3",
        "file": "159781143"
    },
    {
        "title": "a0959131344_16.jpg",
        "description": "Fragment",
        "file": "a0959131344_16.jpg"
    },
    {
        "title": "images",
        "description": "Film",
        "file": "images"
    },
    {
        "title": "other_icon.png",
        "description": "Other",
        "file": "other_icon.png"
    }
]